{
  "\u0000plugin-vue:export-helper": [
    "/build/assets/AppLayout-CY6i5iTz.js"
  ],
  "node_modules/laravel-vite-plugin/inertia-helpers/index.js": [],
  "resources/js/Components/Footer.vue": [
    "/build/assets/AppLayout-CY6i5iTz.js"
  ],
  "resources/js/Components/MetaTags.vue": [
    "/build/assets/Home-DIXQeML7.js",
    "/build/assets/Home-B10KMzyl.css"
  ],
  "resources/js/Components/PrayerTime.vue": [
    "/build/assets/Home-DIXQeML7.js",
    "/build/assets/Home-B10KMzyl.css"
  ],
  "resources/js/Components/PrayerTime.vue?vue&type=style&index=0&lang.css": [
    "/build/assets/Home-DIXQeML7.js",
    "/build/assets/Home-B10KMzyl.css"
  ],
  "resources/js/Components/Search.vue": [
    "/build/assets/AppLayout-CY6i5iTz.js"
  ],
  "resources/js/Components/Spinner.vue": [
    "/build/assets/Home-DIXQeML7.js",
    "/build/assets/Home-B10KMzyl.css"
  ],
  "resources/js/Composables/useLanguageToggle.js": [
    "/build/assets/Home-DIXQeML7.js",
    "/build/assets/Home-B10KMzyl.css"
  ],
  "resources/js/Composables/useTimeFormat.js": [
    "/build/assets/Home-DIXQeML7.js",
    "/build/assets/Home-B10KMzyl.css"
  ],
  "resources/js/Layouts/AppLayout.vue": [
    "/build/assets/AppLayout-CY6i5iTz.js"
  ],
  "resources/js/Pages/Home.vue": [
    "/build/assets/Home-DIXQeML7.js",
    "/build/assets/Home-B10KMzyl.css"
  ],
  "resources/js/Pages/Main.vue": [
    "/build/assets/Main-DRMT2Vt-.js"
  ],
  "resources/js/Stores/citiesStore.js": [
    "/build/assets/AppLayout-CY6i5iTz.js"
  ],
  "resources/js/ssr.js": [],
  "vendor/tightenco/ziggy/dist/index.js": []
}